formeval/__init__.py
formeval/base_evaluator.py
formeval/bleu.py
formeval/cider.py
formeval/evaluator.py
formeval/nca.py
formeval/nca_demo.py
formeval/ngram.py
formeval/nltk_bleu.py
formeval/processor.py
formeval/setup.py
formeval/spice.py
formeval/utils.py
formeval-1.0.6.dist-info/LICENSE
formeval-1.0.6.dist-info/METADATA
formeval-1.0.6.dist-info/WHEEL
formeval-1.0.6.dist-info/top_level.txt
formeval-1.0.6.dist-info/RECORD
