Metadata-Version: 2.1
Name: formeval
Version: 1.0.6
Summary: Language Form Evaluation for Python
Home-page: https://github.com/sudongqi/formeval.git
Author: Dongqi Su
Classifier: Programming Language :: Python :: 3
Classifier: License :: OSI Approved :: MIT License
Classifier: Operating System :: OS Independent
Requires-Python: >=3.6
License-File: LICENSE
Requires-Dist: nltk (>=3.5)
Requires-Dist: lemminflect (>=0.22)
